clustering.py
makima.py
pade.py
rvp.py
stabilization.py
automatic_rvp-1.0.4.dist-info/LICENSE
automatic_rvp-1.0.4.dist-info/METADATA
automatic_rvp-1.0.4.dist-info/WHEEL
automatic_rvp-1.0.4.dist-info/top_level.txt
automatic_rvp-1.0.4.dist-info/RECORD
