Metadata-Version: 2.1
Name: automatic-rvp
Version: 1.0.4
Summary: RVP Program
Home-page: https://github.com/haritan/RVP
Author: Yochai Safrai
Author-email: yochai.safrai@gmail.com
Maintainer: Idan Haritan
Maintainer-email: idan.haritan@gmail.com
License: UNKNOWN
Platform: UNKNOWN
Classifier: Programming Language :: Python :: 3
Classifier: Programming Language :: Python :: 3.7
Requires-Python: >=3.7
License-File: LICENSE
Requires-Dist: numpy
Requires-Dist: scipy
Requires-Dist: matplotlib
Requires-Dist: pandas
Requires-Dist: scikit-learn
Requires-Dist: sympy
